helper/__init__.py
helper/authentication.py
utils/__init__.py
utils/configuration.py
utils/http.py
api_testing-1.0.3.dist-info/LICENSE
api_testing-1.0.3.dist-info/METADATA
api_testing-1.0.3.dist-info/WHEEL
api_testing-1.0.3.dist-info/top_level.txt
api_testing-1.0.3.dist-info/RECORD
