Metadata-Version: 2.1
Name: api-testing
Version: 1.0.3
Summary: API Testing framework for functional testing of REST APIs
Home-page: https://github.com/luvsharma19/api-testing
Author: luv sharma
License: MIT
Project-URL: Source code on GitHub, https://github.com/luvsharma19/api-testing
Keywords: rest api testing,api testing,api tests,rest api,testing,pytest
Platform: UNKNOWN
Classifier: Development Status :: 5 - Production/Stable
Classifier: License :: OSI Approved :: MIT License
Classifier: Topic :: Software Development :: Testing
Classifier: Topic :: Software Development :: Testing :: Acceptance
Classifier: Programming Language :: Python :: 3.7
Requires-Python: >=3.7
Requires-Dist: requests
Requires-Dist: flake8
Requires-Dist: pytest
